{
    "welcome_title": "欢迎使用 AssetRipper",
    "config_options": "配置选项",
    "disable_scripts": "禁用脚本处理",
    "skip_streaming_assets": "跳过 StreamingAssets 文件夹",
    "mesh_export_title": "网格导出格式",
    "audio_export_title": "音频导出格式",
    "image_export_title": "图像导出格式",
    "sprite_export_title": "Sprite 导出格式",
    "terrain_export_title": "地形导出格式",
    "text_asset_export_title": "TextAsset 导出格式",
    "mesh_format_native": "原生格式",
    "mesh_format_native_description": "在Unity编辑器中使用的网格格式. 可以通过多种unity packages转换成其他格式.",
    "mesh_format_obj": "OBJ",
    "mesh_format_obj_description": "广泛使用的基于文本的网格格式，可在几乎所有3D编辑软件中使用。但是，这会断开网格资源的导出引用。",
    "mesh_format_stl_ascii": "STL (ASCII)",
    "mesh_format_stl_ascii_description": "3D 打印常用的 3D 对象格式。 Unity 无法导入此类资源或者文本变体。",
    "mesh_format_stl_binary": "STL (二进制文件)",
    "mesh_format_stl_binary_description": "3D 打印常用的 3D 对象格式。 Unity 无法导入这种类型的资源以及 二进制变体。",
    "mesh_format_glb_primitive": "GLB文件",
    "mesh_format_glb_primitive_description": "FBX 的高质量开源替代品。 GLTF 的二进制版本。 仅包含网格数据。 可能会出错。 Unity 无法导入这种资源。",
    "audio_format_native": "Raw原生格式",
    "audio_format_native_description": "原始FSB音频。无法导入到Unity中，仅建议高级用户使用。",
    "audio_format_default": "默认",
    "audio_format_default_description": "将资源导出为嵌入在FSB中的内容类型。大多数音频类型都导出为wav，有些导出为ogg。",
    "audio_format_force_wav": "转换为 WAV",
    "audio_format_force_wav_description": "将所有音频文件转换为 WAV 文件。 不推荐导入unity，因为它可能会重新压缩文件，导致质量损失。",
    "audio_format_force_mp3": "转换为 MP3",
    "audio_format_force_mp3_description": "将所有音频文件转换为 MP3 文件。 不推荐，因为它会重新压缩文件，导致质量下降。 仅限 Windows。",
    "image_format_description": "影响所有导出的图像",
    "sprite_format_yaml": "Yaml 资源",
    "sprite_format_yaml_description": "导出为可在 Unity Editor 中查看的 Yaml 资源。这是能够精确恢复 Sprite 的元数据的唯一模式。",
    "sprite_format_native": "Unity",
    "sprite_format_native_description": "以Unity Sprite 格式导出。 无法在 Unity 之外查看。",
    "sprite_format_texture": "纹理",
    "sprite_format_texture_description": "导出为 Sprite Sheet 的图像。 可以在 Unity 之外查看，但导出速度较慢。",
    "terrain_format_native": "Unity",
    "terrain_format_native_description": "以原生Unity地形格式导出。 如果您打算重新导入到Unity，这是最有用的选项。",
    "terrain_format_obj": "3D模型（OBJ文件）",
    "terrain_format_obj_description": "将地形导出为 OBJ 格式的 3D 模型，适合使用各种 3D 编辑器查看。 实验性功能； 模型没有正确的缩放。",
    "terrain_format_heatmap": "高度图",
    "terrain_format_heatmap_description": "导出每个位置地形高度的热图。 只有在您不关心细节或 3D 地形时才真正有用。",
    "text_asset_format_binary": "Bytes",
    "text_asset_format_binary_description": "使用 .bytes 扩展名导出TextAsset的原始二进制数据。",
    "text_asset_format_text": "纯文本",
    "text_asset_format_text_description": "导出为纯文本文件 (.txt)",
    "text_asset_format_parse": "解析",
    "text_asset_format_parse_description": "导出为纯文本文件，将尝试猜测正确的文件扩展名(例如 JSON 文件将使用 .json 扩展名)",
    "config_screen_drag_drop_prompt": "请注意，某些设置更改可能会产生或导致错误.\n准备好后，将你的游戏文件/文件夹拖放到此窗口中，或使用左上角的菜单手动打开它们。",
    "menu_file": "文件",
    "menu_file_open_file": "打开文件",
    "menu_file_open_folder": "打开目录",
    "menu_file_reset": "重置",
    "menu_file_exit": "关闭",
    "menu_export": "导出",
    "menu_export_all": "导出所有文件",
    "menu_export_selected": "导出选中文件",
    "menu_language": "语言",
    "loading_game_content_from": "从 {0} \n{1}载入游戏内容",
    "loading_step_load_assemblies": "加载程序集",
    "loading_step_parse_bundle": "解析Bundle资源 {0}",
    "loading_step_parse_archive": "解析存档文件 {0}",
    "loading_step_parse_web": "解析网页文件 {0}",
    "loading_step_parse_serialized": "解析序列化文件 {0}",
    "loading_step_parse_resource": "解析资源文件 {0}",
    "loading_step_parse_il2cpp_metadata": "解析 IL2CPP 元数据",
    "loading_step_generate_dummy_dll": "从 IL2CPP 生成 Mono 程序集",
    "loading_step_locate_key_functions": "扫描库函数的 IL2CPP 二进制文件",
    "loading_step_restore_attributes": "恢复生成的程序集的属性",
    "loading_step_load_assets_from_file": "从 {0} 加载资源",
    "loading_step_detect_platform": "检索文件检测游戏结构",
    "loading_step_initialize_layout": "初始化资源布局",
    "loading_step_create_file_collection": "创建文件集合",
    "loading_step_begin_scheme_processing": "开始处理方案",
    "loading_step_pre_processing": "预处理文件",
    "select_asset_to_view_info": "请在左侧选择资源以显示有关它的信息",
    "asset_tab_basic": "基本信息",
    "asset_tab_yaml": "Yaml",
    "asset_tab_image": "图像",
    "asset_tab_text": "文本",
    "asset_tab_audio": "音频",
    "asset_tab_audio_play": "播放",
    "asset_tab_audio_pause": "暂停",
    "asset_tab_audio_duration_unknown": "<未知>",
    "error": "错误",
    "success": "成功！",
    "export_complete": "导出成功！",
    "no_game_files_found": "在导入的文件中未找到Unity游戏文件或Asset Bundle。",
    "export_deleting_old_files": "清除现有文件中...",
    "export_preparing": "正在准备导出...\n这可能需要几分钟。",
    "export_in_progress_no_file_count_yet": "正在导出资源文件\n0.0%\n?/?",
    "export_in_progress": "正在导出资源文件\n{0}%\n{1}/{2}",
    "error_exporting_with_reason": "导出游戏内容失败: {0}",
    "error_importing_with_reason": "加载游s戏内容失败: {0}",
    "loose_file_saved_at": "文件已保存至 {0}",
    "mesh_format_fbx_primitive_description": "适用于几乎所有3D编辑软件的行业标准格式，包括Unity。因为文件只包含网格数据，所以这会破坏对网格资源的导出引用。",
    "mesh_format_fbx_primitive": "FBX文件",
    "script_content_level_2_description": "默认。这会导出 Mono 游戏的完整方法和 IL2Cpp 游戏的虚拟方法。",
    "c_sharp_langage_version_config_9_0": "C# 9",
    "c_sharp_langage_version_config_10_0": "C# 10",
    "c_sharp_langage_version_config_7": "C# 7",
    "script_content_level_title": "脚本解析等级",
    "script_language_version_title": "C#语言版本",
    "script_content_level_0": "0级",
    "script_content_level_2": "2级",
    "script_content_level_3": "3级",
    "script_content_level_4": "4级",
    "script_content_level_0_description": "脚本没有被导出。",
    "script_content_level_1_description": "方法从反编译导出中剥离。",
    "script_content_level_3_description": "尽可能安全地恢复 IL2Cpp 函数。",
    "script_content_level_4_description": "在不考虑安全性的情况下恢复 IL2Cpp 方法。",
    "c_sharp_langage_version_config_1": "C# 1",
    "c_sharp_langage_version_config_2": "C# 2",
    "c_sharp_langage_version_config_3": "C# 3",
    "c_sharp_langage_version_config_4": "C# 4",
    "c_sharp_langage_version_config_5": "C# 5",
    "c_sharp_langage_version_config_6": "C# 6",
    "ignore_asset_bundle_content_paths": "忽略AssetBundle包内容路径",
    "script_content_level_1": "1级",
    "c_sharp_langage_version_config_7_1": "C# 7.1",
    "menu_export_selected_type": "导出所选类型的所有文件",
    "check_log_for_more_details": "查看日志以获取更多详细信息",
    "mesh_format_ply_ascii": "PLY (ASCII)",
    "mesh_format_ply_ascii_description": "Stanford Triangle Format格式。 Unity 无法导入此类资源。基于文本的变体。",
    "c_sharp_langage_version_config_7_2": "C# 7.2",
    "c_sharp_language_version_config_description": "反编译脚本时要使用的 C# 语言版本。",
    "c_sharp_langage_version_config_7_3": "C# 7.3",
    "c_sharp_langage_version_config_8_0": "C# 8",
    "c_sharp_langage_version_config_latest": "C# 最新版",
    "c_sharp_langage_version_config_auto_safe": "自动 - 安全",
    "c_sharp_langage_version_config_auto_experimental": "自动 - 实验性",
    "shader_asset_export_title": "Shader 导出格式",
    "shader_asset_format_dummy_description": "将Shader导出为Dummy Shader。 只保留了 Properties 和 FallBack 之类的数据，它使用了通用的、不透明的Shader代码。",
    "script_export_format_decompiled_description": "ILSpy 反编译器用于反编译生成 C# 源码。 这是一个可靠的方式 ，但同时非常耗时并且可能会包含许多编译错误。",
    "script_export_title": "脚本导出格式",
    "shader_asset_format_dummy": "Dummy Shader(生成模板Shader)",
    "shader_asset_format_yaml": "Yaml 资源",
    "shader_asset_format_yaml_description": "将Shader导出为 yaml 资源。 实验性功能，仅可用于在Unity Editor中查看。 Editor可以随意破坏这些文件。",
    "shader_asset_format_disassembly": "反汇编",
    "shader_asset_format_disassembly_description": "将Shader反编译并导出。 实验性功能，容易损坏Shader。 这不会在Unity Editor中编译。",
    "script_export_format_decompiled": "反编译",
    "script_export_format_dll_with_renaming": "导出重命名后的Dll",
    "script_export_format_dll_without_renaming": "导出未重命名的Dll",
    "script_export_format_dll_without_renaming_description": "程序集以编译的 Dll 形式导出。 实验性功能，可能完全不起作用。",
    "script_export_format_hybrid": "Hybrid",
    "not_implemented_yet": "尚未实现"
}
